zipToCBSA/__init__.py
zipToCBSA/cli.py
zipToCBSA/zipToCBSA.py
zipToCBSA/data/metadata.json
zipToCBSA/data/zip-cbsa.csv
ziptocbsa-1.0.1.dist-info/METADATA
ziptocbsa-1.0.1.dist-info/WHEEL
ziptocbsa-1.0.1.dist-info/entry_points.txt
ziptocbsa-1.0.1.dist-info/licenses/LICENSE
ziptocbsa-1.0.1.dist-info/RECORD
