Metadata-Version: 2.4
Name: zipToCBSA
Version: 1.0.1
Summary: A small package designed to help convert USPS ZIP Codes to OMB CBSA Codes
Project-URL: Homepage, https://github.com/pypa/sampleproject
Project-URL: Issues, https://github.com/pypa/sampleproject/issues
Author-email: Eric Renfert <ericrenfert@hotmail.com>
License-Expression: MIT
License-File: LICENSE
Classifier: Operating System :: OS Independent
Classifier: Programming Language :: Python :: 3
Requires-Python: >=3.9
Requires-Dist: importlib
Requires-Dist: pandas
